escherauth/__init__.py
escherauth/escherauth.py
escherauth-2.0.1.dist-info/licenses/LICENSE
escherauth-2.0.1.dist-info/METADATA
escherauth-2.0.1.dist-info/WHEEL
escherauth-2.0.1.dist-info/top_level.txt
escherauth-2.0.1.dist-info/RECORD
