Metadata-Version: 2.4
Name: escherauth
Version: 2.0.1
Summary: Python implementation of the AWS4 compatible Escher HTTP request signing protocol.
Home-page: http://escherauth.io/
Download-URL: https://github.com/emartech/escher-python
Author: Emarsys Security
Author-email: security@emarsys.com
License: MIT
Classifier: Development Status :: 4 - Beta
Classifier: Environment :: Console
Classifier: Programming Language :: Python
Classifier: Intended Audience :: Developers
Classifier: Environment :: Plugins
Classifier: License :: OSI Approved :: MIT License
Classifier: Topic :: Internet :: WWW/HTTP
Classifier: Topic :: Utilities
License-File: LICENSE
Requires-Dist: requests<3.0.0,>=2.0.0
Dynamic: author
Dynamic: author-email
Dynamic: classifier
Dynamic: description
Dynamic: description-content-type
Dynamic: download-url
Dynamic: home-page
Dynamic: license
Dynamic: license-file
Dynamic: requires-dist
Dynamic: summary
